odoo8_addon_web_ir_actions_act_window_page-8.0.1.0.0.99.dev3-py2.7-nspkg.pth
odoo8_addon_web_ir_actions_act_window_page-8.0.1.0.0.99.dev3.dist-info/METADATA
odoo8_addon_web_ir_actions_act_window_page-8.0.1.0.0.99.dev3.dist-info/RECORD
odoo8_addon_web_ir_actions_act_window_page-8.0.1.0.0.99.dev3.dist-info/WHEEL
odoo8_addon_web_ir_actions_act_window_page-8.0.1.0.0.99.dev3.dist-info/namespace_packages.txt
odoo8_addon_web_ir_actions_act_window_page-8.0.1.0.0.99.dev3.dist-info/top_level.txt
odoo_addons/web_ir_actions_act_window_page/README.md
odoo_addons/web_ir_actions_act_window_page/__init__.py
odoo_addons/web_ir_actions_act_window_page/__openerp__.py
odoo_addons/web_ir_actions_act_window_page/i18n/web_ir_actions_act_window_page.pot
odoo_addons/web_ir_actions_act_window_page/static/description/icon.png
odoo_addons/web_ir_actions_act_window_page/static/src/js/web_ir_actions_act_window_page.js
odoo_addons/web_ir_actions_act_window_page/view/qweb.xml
